agora/__init__.py
agora/admin.py
agora/apps.py
agora/models.py
agora/tests.py
agora/views.py
agora/static/.DS_Store
agora/static/css/style.css
agora/static/img/apple-touch-icon.png
agora/static/img/favicon.png
agora/static/img/logo.png
agora/static/js/AgoraRTCSDK-3.0.2.js
agora/static/js/agora.js
agora/static/js/index.js
agora/templates/index.html
django_agora-0.4.dist-info/LICENSE
django_agora-0.4.dist-info/METADATA
django_agora-0.4.dist-info/WHEEL
django_agora-0.4.dist-info/top_level.txt
django_agora-0.4.dist-info/RECORD
